{
  "sum_response_time": [
    19,
    14,
    9,
    9,
    8,
    8,
    8,
    8,
    10,
    16,
    8,
    14,
    16,
    13,
    8,
    13,
    8,
    8,
    7,
    8,
    9,
    8,
    7,
    8,
    8,
    8,
    8,
    8,
    8,
    7,
    7,
    8,
    8,
    11,
    8,
    8,
    7,
    8,
    8,
    7,
    16,
    13,
    8,
    13,
    7,
    8,
    8,
    8,
    8,
    8
  ],
  "total_transaction_time": [
    0,
    0,
    0,
    0,
    0,
    0,
    0,
    0,
    0,
    0,
    0,
    0,
    0,
    0,
    0,
    0,
    0,
    0,
    0,
    0,
    0,
    0,
    0,
    0,
    0,
    0,
    0,
    0,
    0,
    0,
    0,
    0,
    0,
    0,
    0,
    0,
    0,
    0,
    0,
    0,
    0,
    0,
    0,
    0,
    0,
    0,
    0,
    0,
    0,
    0
  ],
  "api_call_count": 1,
  "cpu_used_by_server": [
    85559.86,
    85566.01,
    85574.4,
    85577.81,
    85580.59,
    85583.34,
    85586.16,
    85589.38,
    85592.13,
    85597.04,
    85606.55,
    85610.66,
    85617.51,
    85626.93,
    85634.79,
    85638.1,
    85644.08,
    85646.76,
    85649.75,
    85652.34,
    85654.84,
    85658.8,
    85661.4,
    85664.24,
    85666.8,
    85669.35,
    85671.84,
    85675.39,
    85677.92,
    85680.78,
    85683.29,
    85685.97,
    85688.49,
    85691.16,
    85694.2,
    85696.85,
    85699.37,
    85701.87,
    85704.43,
    85707,
    85709.85,
    85720.05,
    85726.24,
    85728.76,
    85736.6,
    85739.01,
    85742.11,
    85744.54,
    85747.58,
    85749.98
  ],
  "memory_used_by_server": [
    27.71,
    28.45,
    29.14,
    26.67,
    27.35,
    28.02,
    28.69,
    26.17,
    26.85,
    27.53,
    28.21,
    28.88,
    26.38,
    27.04,
    27.7,
    28.36,
    29.05,
    29.7,
    26.6,
    27.25,
    27.89,
    28.55,
    29.2,
    26.57,
    27.21,
    27.86,
    28.51,
    29.16,
    29.81,
    26.65,
    27.52,
    28.17,
    28.82,
    29.48,
    26.94,
    27.6,
    28.24,
    28.89,
    29.54,
    30.19,
    27.02,
    27.7,
    28.35,
    29.02,
    29.65,
    30.31,
    27.48,
    28.11,
    28.75,
    29.41
  ],
  "total_data_transferred": [
    12438,
    12438,
    12438,
    12438,
    12438,
    12438,
    12438,
    12438,
    12438,
    12438,
    12438,
    12438,
    12438,
    12438,
    12438,
    12438,
    12438,
    12438,
    12438,
    12438,
    12438,
    12438,
    12438,
    12438,
    12438,
    12438,
    12438,
    12438,
    12438,
    12438,
    12438,
    12438,
    12438,
    12438,
    12438,
    12438,
    12438,
    12438,
    12438,
    12438,
    12438,
    12438,
    12438,
    12438,
    12438,
    12438,
    12438,
    12438,
    12438,
    12438
  ]
}