{
  "duration_of_all_calls": [
    12,
    15,
    12,
    17,
    14,
    7,
    5,
    12,
    6,
    9,
    5,
    5,
    13,
    10,
    6,
    10,
    6,
    6,
    12,
    11,
    6,
    6,
    5,
    11,
    7,
    9,
    6,
    9,
    6,
    6,
    11,
    6,
    9,
    7,
    6,
    12,
    6,
    19,
    10,
    5,
    7,
    11,
    6,
    9,
    6,
    6,
    9,
    5,
    8,
    6
  ],
  "total_transaction_time": [
    0,
    0,
    0,
    0,
    0,
    0,
    0,
    0,
    0,
    0,
    0,
    0,
    0,
    0,
    0,
    0,
    0,
    0,
    0,
    0,
    0,
    0,
    0,
    0,
    0,
    0,
    0,
    0,
    0,
    0,
    0,
    0,
    0,
    0,
    0,
    0,
    0,
    0,
    0,
    0,
    0,
    0,
    0,
    0,
    0,
    0,
    0,
    0,
    0,
    0
  ],
  "api_call_count": 1,
  "cpu_used_by_server": [
    4047.07,
    4050.71,
    4053.96,
    4058.16,
    4061.55,
    4064.19,
    4067.27,
    4069.75,
    4073.61,
    4075.87,
    4079.81,
    4082.69,
    4085.61,
    4089.28,
    4092.95,
    4101.86,
    4104.43,
    4106.96,
    4111.54,
    4121.15,
    4123.7,
    4126.78,
    4129.81,
    4132.76,
    4136.51,
    4139.77,
    4142.4,
    4145.78,
    4148.42,
    4151.88,
    4158.6,
    4161.35,
    4165.81,
    4177.52,
    4184.28,
    4187.79,
    4195.07,
    4197.79,
    4200.83,
    4203.55,
    4206.71,
    4210.55,
    4223.98,
    4228.34,
    4230.82,
    4233.26,
    4236.17,
    4239.01,
    4241.66,
    4248.17
  ],
  "memory_used_by_server": [
    38.51,
    39.93,
    41.28,
    29.43,
    30.78,
    32.12,
    33.47,
    34.81,
    36.16,
    37.5,
    38.85,
    40.19,
    41.53,
    29.65,
    30.99,
    32.33,
    33.68,
    35.01,
    36.36,
    37.72,
    39.05,
    40.38,
    41.71,
    29.77,
    31.12,
    32.45,
    33.78,
    35.12,
    36.44,
    37.77,
    39.12,
    40.44,
    41.77,
    29.97,
    31.35,
    32.67,
    34.02,
    35.35,
    36.68,
    38,
    39.33,
    40.67,
    42,
    30.26,
    31.58,
    32.91,
    34.24,
    35.58,
    36.9,
    38.24
  ],
  "total_data_transferred": [
    4209,
    4209,
    4209,
    4209,
    4209,
    4209,
    4209,
    4209,
    4209,
    4209,
    4209,
    4209,
    4209,
    4209,
    4209,
    4209,
    4209,
    4209,
    4209,
    4209,
    4209,
    4209,
    4209,
    4209,
    4209,
    4209,
    4209,
    4209,
    4209,
    4209,
    4209,
    4209,
    4209,
    4209,
    4209,
    4209,
    4209,
    4209,
    4209,
    4209,
    4209,
    4209,
    4209,
    4209,
    4209,
    4209,
    4209,
    4209,
    4209,
    4209
  ]
}